{
  "$schema": "https://turbo.build/schema.json",
  "globalDependencies": [
    "pnpm-lock.yaml",
    "patches",
    ".env",
    ".env.testing",
    ".eslintignore",
    ".prettierrc.json",
    ".eslintrc.cjs",
    "rollup.config.mjs",
    "vite.config.mts",
    ".github/workflows/ci.yml",
    "tsconfig.json",
    "tsconfig.dist.json",
    "*/tsconfig.json",
    "packages/*/tsconfig.json",
    "packages/@glimmer/.eslintrc.cjs",
    "packages/@glimmer-workspace/.eslintrc.cjs",
    "packages/@glimmer-workspace/eslint-plugin/**/*",
    "packages/@glimmer-workspace/build/lib/config.js"
  ],
  "tasks": {
    "lint:all": {
      "cache": false,
      "dependsOn": ["test:lint", "test:publint"]
    },
    "test:node": {},
    "test:lint": {},
    "test:publint": {
      "dependsOn": ["prepack", "prepare"]
    },
    "prepare": {
      "dependsOn": ["prepack"],
      "outputs": ["dist/**"]
    },
    "prepack": {
      "outputs": ["dist/**"],
      "dependsOn": ["^prepack"]
    },
    "//#test:lint": {
      "dependsOn": ["//#repo:update:conventions", "//#repo:update:metadata"]
    },
    "//#repo:update:conventions": {},
    "//#repo:update:metadata": {},
    "//#test:types": {
      "inputs": ["**/dist/**", "tsconfig.dist.json"],
      "dependsOn": ["^prepack", "//#benchmark:setup", "//#smoke:setup"]
    },
    "//#benchmark:setup": {
      "outputs": ["./benchmark/benchmarks/krausest/packages"],
      "dependsOn": ["^prepack"]
    },
    "//#smoke:setup": {
      "outputs": ["./smoke-tests/node/packages"],
      "dependsOn": ["^prepack"]
    }
  }
}
